{
  "captured_at" : "2026-07-12T15:07:59Z",
  "impact_frame_index" : 20,
  "frame_count" : 41,
  "timestamps" : [
    {
      "frame_index" : 0,
      "timestamp" : 24667.311973291002
    },
    {
      "timestamp" : 24667.328615999999,
      "frame_index" : 1
    },
    {
      "frame_index" : 2,
      "timestamp" : 24667.341097875
    },
    {
      "frame_index" : 3,
      "timestamp" : 24667.357740374999
    },
    {
      "timestamp" : 24667.378543625,
      "frame_index" : 4
    },
    {
      "frame_index" : 5,
      "timestamp" : 24667.395186165999
    },
    {
      "frame_index" : 6,
      "timestamp" : 24667.411828749999
    },
    {
      "timestamp" : 24667.432632,
      "frame_index" : 7
    },
    {
      "timestamp" : 24667.449274540999,
      "frame_index" : 8
    },
    {
      "frame_index" : 9,
      "timestamp" : 24667.461756416
    },
    {
      "frame_index" : 10,
      "timestamp" : 24667.478399125001
    },
    {
      "frame_index" : 11,
      "timestamp" : 24667.486720375
    },
    {
      "frame_index" : 12,
      "timestamp" : 24667.499202291001
    },
    {
      "frame_index" : 13,
      "timestamp" : 24667.511684165998
    },
    {
      "timestamp" : 24667.524166125,
      "frame_index" : 14
    },
    {
      "frame_index" : 15,
      "timestamp" : 24667.536648041001
    },
    {
      "timestamp" : 24667.549130040999,
      "frame_index" : 16
    },
    {
      "timestamp" : 24667.561611958001,
      "frame_index" : 17
    },
    {
      "timestamp" : 24667.574093915999,
      "frame_index" : 18
    },
    {
      "frame_index" : 19,
      "timestamp" : 24667.586575791
    },
    {
      "frame_index" : 20,
      "timestamp" : 24667.594897040999
    },
    {
      "frame_index" : 21,
      "timestamp" : 24667.611539665999
    },
    {
      "frame_index" : 22,
      "timestamp" : 24667.624021583
    },
    {
      "timestamp" : 24667.636503500002,
      "frame_index" : 23
    },
    {
      "timestamp" : 24667.648985415999,
      "frame_index" : 24
    },
    {
      "frame_index" : 25,
      "timestamp" : 24667.661467333
    },
    {
      "timestamp" : 24667.678110000001,
      "frame_index" : 26
    },
    {
      "timestamp" : 24667.690591957999,
      "frame_index" : 27
    },
    {
      "frame_index" : 28,
      "timestamp" : 24667.703073833
    },
    {
      "timestamp" : 24667.719716332998,
      "frame_index" : 29
    },
    {
      "timestamp" : 24667.728037583001,
      "frame_index" : 30
    },
    {
      "frame_index" : 31,
      "timestamp" : 24667.744680208001
    },
    {
      "frame_index" : 32,
      "timestamp" : 24667.753001624998
    },
    {
      "timestamp" : 24667.761322833001,
      "frame_index" : 33
    },
    {
      "timestamp" : 24667.777965375,
      "frame_index" : 34
    },
    {
      "frame_index" : 35,
      "timestamp" : 24667.786286708
    },
    {
      "frame_index" : 36,
      "timestamp" : 24667.798768583001
    },
    {
      "timestamp" : 24667.807089875001,
      "frame_index" : 37
    },
    {
      "frame_index" : 38,
      "timestamp" : 24667.819571749998
    },
    {
      "frame_index" : 39,
      "timestamp" : 24667.827893165999
    },
    {
      "timestamp" : 24667.840375,
      "frame_index" : 40
    }
  ]
}